euroleague_scrapping/Euroscrapper.py
euroleague_scrapping/__init__.py
euroleague_scrapping/example.py
euroleague_scrapping/utils.py
euroleague_scrapping-0.0.1.dev21.dist-info/AUTHORS
euroleague_scrapping-0.0.1.dev21.dist-info/LICENSE.txt
euroleague_scrapping-0.0.1.dev21.dist-info/METADATA
euroleague_scrapping-0.0.1.dev21.dist-info/WHEEL
euroleague_scrapping-0.0.1.dev21.dist-info/pbr.json
euroleague_scrapping-0.0.1.dev21.dist-info/top_level.txt
euroleague_scrapping-0.0.1.dev21.dist-info/RECORD
